graphwiselearn/__init__.py
graphwiselearn/gwl_cmd.py
graphwiselearn/gwl_web.py
graphwiselearn/version.py
graphwiselearn-0.1.0.dist-info/METADATA
graphwiselearn-0.1.0.dist-info/WHEEL
graphwiselearn-0.1.0.dist-info/entry_points.txt
graphwiselearn-0.1.0.dist-info/licenses/LICENSE
graphwiselearn-0.1.0.dist-info/RECORD
