Metadata-Version: 2.3
Name: GraphWiseLearn
Version: 0.1.0
Summary: Personalized Learning enabled by Semantification
Project-URL: Home, https://github.com/WolfgangFahl/GraphWiseLearn
Project-URL: Documentation, https://wiki.bitplan.com/index.php/GraphWiseLearn
Project-URL: Source, https://github.com/WolfgangFahl/GraphWiseLearn
Author-email: Wolfgang Fahl <wf@WolfgangFahl.com>
Maintainer-email: Wolfgang Fahl <wf@WolfgangFahl.com>
License: Apache-2.0
License-File: LICENSE
Keywords: TEL,competence,learning,nicegui,skills
Classifier: Development Status :: 4 - Beta
Classifier: Environment :: Web Environment
Classifier: Intended Audience :: Developers
Classifier: Intended Audience :: Education
Classifier: Intended Audience :: Science/Research
Classifier: License :: OSI Approved :: Apache Software License
Classifier: Operating System :: OS Independent
Classifier: Programming Language :: Python :: 3 :: Only
Classifier: Programming Language :: Python :: 3.9
Classifier: Programming Language :: Python :: 3.10
Classifier: Programming Language :: Python :: 3.11
Classifier: Programming Language :: Python :: 3.12
Classifier: Topic :: Software Development :: User Interfaces
Requires-Python: >=3.9
Requires-Dist: ngwidgets>=0.15.1
Provides-Extra: test
Requires-Dist: green; extra == 'test'
